anime_info/__init__.py
anime_info/main.py
anime_info_cli-2.0.dist-info/METADATA
anime_info_cli-2.0.dist-info/WHEEL
anime_info_cli-2.0.dist-info/entry_points.txt
anime_info_cli-2.0.dist-info/top_level.txt
anime_info_cli-2.0.dist-info/RECORD
