Metadata-Version: 2.1
Name: anime-info-cli
Version: 2.0
Summary: A simple CLI application to fetch information such as title, genre, or ranking for any anime.
Home-page: https://github.com/deinusername/anime-info-cli
Author: Moritz Maier
Author-email: moritzmaier353@gmail.com
License: UNKNOWN
Platform: UNKNOWN
Classifier: Programming Language :: Python :: 3
Classifier: License :: OSI Approved :: MIT License
Classifier: Operating System :: OS Independent
Requires-Python: >=3.7
